{"0": {
    "doc": "About",
    "title": "About",
    "content": "This is the base Jekyll theme. You can find out more info about customizing your Jekyll theme, as well as basic Jekyll usage documentation at jekyllrb.com . You can find the source code for Minima at GitHub: jekyll / minima . You can find the source code for Jekyll at GitHub: jekyll / jekyll . ",
    "url": "/about/",
    
    "relUrl": "/about/"
  },"1": {
    "doc": "Categories",
    "title": "Categories",
    "content": ". dev . 테스트 페이지 1 . jekyll . Welcome to Jekyll! . update . Welcome to Jekyll! . 개발 . jekyll post 작성법 . ",
    "url": "/categories/",
    
    "relUrl": "/categories/"
  },"2": {
    "doc": "hihi",
    "title": "Hihi",
    "content": "hello world . All notable user-facing changes to this project are documented in this file. first_post . ",
    "url": "/dev.html#hihi",
    
    "relUrl": "/dev.html#hihi"
  },"3": {
    "doc": "hihi",
    "title": "hihi",
    "content": " ",
    "url": "/dev.html",
    
    "relUrl": "/dev.html"
  }
}
